tirf_ob/__init__.py
tirf_ob/select_from_ROI.py
tirf_ob/version.py
tirf_ob/utils/__init__.py
tirf_ob/utils/find_peaks.py
tirf_ob/utils/load_data.py
tirf_ob-0.1.dist-info/METADATA
tirf_ob-0.1.dist-info/WHEEL
tirf_ob-0.1.dist-info/entry_points.txt
tirf_ob-0.1.dist-info/top_level.txt
tirf_ob-0.1.dist-info/RECORD
